Metadata-Version: 2.1
Name: AstroGlue
Version: 0.1.3
Summary: AstroGlue serves as a bridge between the AstroLink clustering algorithm and the Glue visualization tool with an interactive GUI for handling various inputs
Maintainer-email: Kamalesh Sampath <kamaleshsampath.nitt@gmail.com>
License: MIT
Classifier: Programming Language :: Python :: 3
Classifier: Operating System :: OS Independent
Classifier: License :: OSI Approved :: MIT License
Requires-Python: >=3.8
License-File: LICENSE.md
License-File: COPYING.md
Requires-Dist: numpy<2.0.0
Requires-Dist: pandas
Requires-Dist: PyQt5
Requires-Dist: glueviz==1.2.0
Requires-Dist: glue-qt==0.3.1
Requires-Dist: glue-vispy-viewers==1.1.0
Requires-Dist: astrolink
Provides-Extra: tests
Requires-Dist: pytest; extra == "tests"
Requires-Dist: pytest-cov; extra == "tests"
Requires-Dist: nbval; extra == "tests"
Provides-Extra: docs
Requires-Dist: ipykernel; extra == "docs"
Requires-Dist: nbsphinx; extra == "docs"
Requires-Dist: nbsphinx-link; extra == "docs"
Requires-Dist: sphinx; extra == "docs"
Requires-Dist: sphinx_mdinclude; extra == "docs"
Requires-Dist: sphinx_rtd_theme; extra == "docs"
